tknodesystem/__init__.py
tknodesystem/node.py
tknodesystem/node_args.py
tknodesystem/node_canvas.py
tknodesystem/node_menu.py
tknodesystem/node_socket.py
tknodesystem/node_types.py
tknodesystem/node_wire.py
tknodesystem/grid_images/grid_dot.png
tknodesystem/grid_images/grid_lines.png
tknodesystem/grid_images/no_grid.png
tknodesystem-0.9.dist-info/LICENSE
tknodesystem-0.9.dist-info/METADATA
tknodesystem-0.9.dist-info/WHEEL
tknodesystem-0.9.dist-info/dependency_links.txt
tknodesystem-0.9.dist-info/top_level.txt
tknodesystem-0.9.dist-info/RECORD
