Metadata-Version: 2.1
Name: tknodesystem
Version: 0.9
Summary: Simple visual node system (DAG) with tkinter!
Home-page: https://github.com/Akascape/TkNodeSystem
Author: Akash Bora
License: MIT
Keywords: customtkinter,tkinter,tkinter-nodes,tknodes,tkinter-DAG,node-system,node-based-ui,tknodesystem,nodes,visual-scripting
Classifier: License :: OSI Approved :: MIT License 
Classifier: Programming Language :: Python :: 3
Classifier: Operating System :: OS Independent
Requires-Python: >=3.6
License-File: LICENSE
Requires-Dist: customtkinter
